{"links": {"self": {"href": "data/repositories/osrf/servicesim/pullrequests/93/comments/60004071.json"}, "code": {"href": "https://api.bitbucket.org/2.0/repositories/osrf/servicesim/diff/osrf/servicesim:e442b4531203..14e6693943aa?path=competitor_example_solution%2Fservicesim_example_python_solution%2Fpackage.xml"}, "html": {"href": "#!/osrf/servicesim/pull-requests/93/_/diff#comment-60004071"}}, "deleted": false, "pullrequest": {"type": "pullrequest", "id": 93, "links": {"self": {"href": "data/repositories/osrf/servicesim/pullrequests/93.json"}, "html": {"href": "#!/osrf/servicesim/pull-requests/93"}}, "title": "Drift example solution"}, "content": {"raw": "this should also be a `build_depend` as the dependency is needed at build time to generate the messages. It should also be listed in the `catkin_package` call as a `CATKIN_DEPEND`", "markup": "markdown", "html": "<p>this should also be a <code>build_depend</code> as the dependency is needed at build time to generate the messages. It should also be listed in the <code>catkin_package</code> call as a <code>CATKIN_DEPEND</code></p>", "type": "rendered"}, "created_on": "2018-03-27T14:31:02.379082+00:00", "user": {"display_name": "mikaelarguedas", "uuid": "{85949490-7d6b-4fd5-9d44-69f087bbe838}", "links": {"self": {"href": "https://api.bitbucket.org/2.0/users/%7B85949490-7d6b-4fd5-9d44-69f087bbe838%7D"}, "html": {"href": "https://bitbucket.org/%7B85949490-7d6b-4fd5-9d44-69f087bbe838%7D/"}, "avatar": {"href": "https://avatar-management--avatars.us-west-2.prod.public.atl-paas.net/557058:7fdd80d3-bc91-4743-83b3-dfaf89946270/90150a0f-25c1-4190-a5ae-408a50b6f652/128"}}, "nickname": "mikaelarguedas", "type": "user", "account_id": "557058:7fdd80d3-bc91-4743-83b3-dfaf89946270"}, "inline": {"to": 26, "from": null, "outdated": true, "path": "competitor_example_solution/servicesim_example_python_solution/package.xml"}, "updated_on": "2018-03-27T14:31:02.383514+00:00", "type": "pullrequest_comment", "id": 60004071}