{"pagelen": 100, "values": [{"changes": {"title": {"new": "Allowed Maximum joints force are not correct", "old": "Allowed Maximum joints forcess are not correct"}}, "links": {"self": {"href": "data/repositories/osrf/robocup3ds/issues/6/changes/20744940.json"}, "html": {"href": "#!/osrf/robocup3ds/issues/6#comment-20744940"}}, "issue": {"links": {"self": {"href": "data/repositories/osrf/robocup3ds/issues/6.json"}}, "type": "issue", "id": 6, "repository": {"links": {"self": {"href": "data/repositories/osrf/robocup3ds.json"}, "html": {"href": "#!/osrf/robocup3ds"}, "avatar": {"href": "data/bytebucket.org/ravatar/{920a9983-6b31-4842-b414-a2a01bf8a4e6}ts=c_plus_plus"}}, "type": "repository", "name": "robocup3ds", "full_name": "osrf/robocup3ds", "uuid": "{920a9983-6b31-4842-b414-a2a01bf8a4e6}"}, "title": "Maximum joints effort are not correct"}, "created_on": "2015-08-06T18:29:32.116073+00:00", "user": {"display_name": "nima shafii", "uuid": "{44717119-2661-4d7f-bedc-6945a1800c8d}", "links": {"self": {"href": "https://api.bitbucket.org/2.0/users/%7B44717119-2661-4d7f-bedc-6945a1800c8d%7D"}, "html": {"href": "https://bitbucket.org/%7B44717119-2661-4d7f-bedc-6945a1800c8d%7D/"}, "avatar": {"href": "https://bitbucket.org/account/nima_sh/avatar/"}}, "nickname": "nima_sh", "type": "user", "account_id": null}, "message": {"raw": null, "markup": "markdown", "html": "", "type": "rendered"}, "type": "issue_change", "id": 20744940}, {"changes": {"content": {"new": "I think that the maximum allowed joint effort are too low to keep the robot upright. In my tests by using many different controller I could not keep the robot upright. This value can be found in sdf file and example of that is given in the following line", "old": "I think that the maximum allowed joint forces are too low to keep the robot upright. In my tests by using many different controller I could not keep the robot upright. This value can be found in sdf file and example of that is given in the following line"}, "title": {"new": "Maximum joints effort are not correct", "old": "Allowed Maximum joints force are not correct"}}, "links": {"self": {"href": "data/repositories/osrf/robocup3ds/issues/6/changes/20745604.json"}, "html": {"href": "#!/osrf/robocup3ds/issues/6#comment-20745604"}}, "issue": {"links": {"self": {"href": "data/repositories/osrf/robocup3ds/issues/6.json"}}, "type": "issue", "id": 6, "repository": {"links": {"self": {"href": "data/repositories/osrf/robocup3ds.json"}, "html": {"href": "#!/osrf/robocup3ds"}, "avatar": {"href": "data/bytebucket.org/ravatar/{920a9983-6b31-4842-b414-a2a01bf8a4e6}ts=c_plus_plus"}}, "type": "repository", "name": "robocup3ds", "full_name": "osrf/robocup3ds", "uuid": "{920a9983-6b31-4842-b414-a2a01bf8a4e6}"}, "title": "Maximum joints effort are not correct"}, "created_on": "2015-08-06T19:08:05.755027+00:00", "user": {"display_name": "nima shafii", "uuid": "{44717119-2661-4d7f-bedc-6945a1800c8d}", "links": {"self": {"href": "https://api.bitbucket.org/2.0/users/%7B44717119-2661-4d7f-bedc-6945a1800c8d%7D"}, "html": {"href": "https://bitbucket.org/%7B44717119-2661-4d7f-bedc-6945a1800c8d%7D/"}, "avatar": {"href": "https://bitbucket.org/account/nima_sh/avatar/"}}, "nickname": "nima_sh", "type": "user", "account_id": null}, "message": {"raw": null, "markup": "markdown", "html": "", "type": "rendered"}, "type": "issue_change", "id": 20745604}, {"changes": {"state": {"new": "resolved", "old": "new"}}, "links": {"self": {"href": "data/repositories/osrf/robocup3ds/issues/6/changes/23075403.json"}, "html": {"href": "#!/osrf/robocup3ds/issues/6#comment-23075403"}}, "issue": {"links": {"self": {"href": "data/repositories/osrf/robocup3ds/issues/6.json"}}, "type": "issue", "id": 6, "repository": {"links": {"self": {"href": "data/repositories/osrf/robocup3ds.json"}, "html": {"href": "#!/osrf/robocup3ds"}, "avatar": {"href": "data/bytebucket.org/ravatar/{920a9983-6b31-4842-b414-a2a01bf8a4e6}ts=c_plus_plus"}}, "type": "repository", "name": "robocup3ds", "full_name": "osrf/robocup3ds", "uuid": "{920a9983-6b31-4842-b414-a2a01bf8a4e6}"}, "title": "Maximum joints effort are not correct"}, "created_on": "2015-11-05T01:17:13.173994+00:00", "user": {"display_name": "Carlos Ag\u00fcero", "uuid": "{da8a8e89-4bb0-421b-bd0e-dbbed3d4ed6a}", "links": {"self": {"href": "https://api.bitbucket.org/2.0/users/%7Bda8a8e89-4bb0-421b-bd0e-dbbed3d4ed6a%7D"}, "html": {"href": "https://bitbucket.org/%7Bda8a8e89-4bb0-421b-bd0e-dbbed3d4ed6a%7D/"}, "avatar": {"href": "data/secure.gravatar.com/avatar/692bf15758111acaddae4da15a47f9e5d=httpsavatar-management--avatars.us-west-2.prod.public.atl-paas.netinitialsCA-0.png"}}, "nickname": "caguero", "type": "user", "account_id": "557058:4ded1ddf-947e-4154-bbd1-3dba24f1bdbd"}, "message": {"raw": "I think that the gains were already updated. Reopen if it's not the case.", "markup": "markdown", "html": "<p>I think that the gains were already updated. Reopen if it's not the case.</p>", "type": "rendered"}, "type": "issue_change", "id": 23075403}], "page": 1, "size": 3}